LICENSE
MANIFEST.in
NOTICE
README.md
pyproject.toml
setup.py
/home/gbrixi/vortex/vortex/ops/attn/csrc/flash_attn/flash_api.cpp
/home/gbrixi/vortex/vortex/ops/attn/csrc/flash_attn/src/flash_bwd_hdim128_bf16_causal_sm80.cu
/home/gbrixi/vortex/vortex/ops/attn/csrc/flash_attn/src/flash_bwd_hdim128_bf16_sm80.cu
/home/gbrixi/vortex/vortex/ops/attn/csrc/flash_attn/src/flash_fwd_hdim128_bf16_causal_sm80.cu
/home/gbrixi/vortex/vortex/ops/attn/csrc/flash_attn/src/flash_fwd_hdim128_bf16_sm80.cu
/home/gbrixi/vortex/vortex/ops/attn/csrc/flash_attn/src/flash_fwd_split_hdim128_bf16_causal_sm80.cu
/home/gbrixi/vortex/vortex/ops/attn/csrc/flash_attn/src/flash_fwd_split_hdim128_bf16_sm80.cu
test/test_backward.py
test/test_evo2_forward.py
test/test_evo2_generation copy.py
test/test_evo2_generation.py
test/test_forward.py
test/test_numerics.py
test/test_prefill.py
vortex/__init__.py
vortex/logging.py
vortex/model/__init__.py
vortex/model/attention.py
vortex/model/cache.py
vortex/model/config.py
vortex/model/engine.py
vortex/model/generation.py
vortex/model/layers.py
vortex/model/model.py
vortex/model/positional_embeddings.py
vortex/model/rotary.py
vortex/model/sample.py
vortex/model/tokenizer.py
vortex/model/utils.py
vortex/ops/__init__.py
vortex/ops/attn_interface.py
vortex/ops/hcl_interface.py
vortex/ops/hcm_interface.py
vortex/ops/hcs_interface.py
vortex/ops/attn/flash_attn_2_cuda.cpython-311-x86_64-linux-gnu.so
vortex/ops/attn/flash_attn_2_cuda.cpython-312-x86_64-linux-gnu.so
vortex/ops/attn/setup.py
vortex/ops/attn/build/lib.linux-x86_64-cpython-311/flash_attn_2_cuda.cpython-311-x86_64-linux-gnu.so
vortex/ops/attn/build/lib.linux-x86_64-cpython-312/flash_attn_2_cuda.cpython-312-x86_64-linux-gnu.so
vortex/ops/attn/csrc/flash_attn/flash_api.cpp
vortex/ops/attn/csrc/flash_attn/src/alibi.h
vortex/ops/attn/csrc/flash_attn/src/block_info.h
vortex/ops/attn/csrc/flash_attn/src/dropout.h
vortex/ops/attn/csrc/flash_attn/src/flash.h
vtx.egg-info/PKG-INFO
vtx.egg-info/SOURCES.txt
vtx.egg-info/dependency_links.txt
vtx.egg-info/not-zip-safe
vtx.egg-info/requires.txt
vtx.egg-info/top_level.txt