Metadata-Version: 2.4
Name: vtx
Version: 1.0.6
Summary: Reference implementation of operators for deep signal processing architectures
Home-page: http://github.com/zymrael/vortex
Author: Michael Poli
License-Expression: Apache-2.0
Requires-Python: >=3.10
License-File: LICENSE
License-File: NOTICE
Requires-Dist: torch<=2.6.1,>=2.5.1
Requires-Dist: transformer_engine[pytorch]==1.13.0
Requires-Dist: numpy
Requires-Dist: einops==0.8.0
Requires-Dist: packaging
Requires-Dist: rich
Requires-Dist: tqdm
Requires-Dist: PyYAML
Dynamic: home-page
Dynamic: license-file
Dynamic: requires-python
